silencewarp/__init__.py
silencewarp/silencewarp.py
silencewarp-0.2.1.dist-info/LICENSE
silencewarp-0.2.1.dist-info/METADATA
silencewarp-0.2.1.dist-info/WHEEL
silencewarp-0.2.1.dist-info/RECORD
