Metadata-Version: 2.3
Name: silencewarp
Version: 0.2.1
Summary: 
Author: Riccardo
Author-email: github@dickon.it
Requires-Python: >=3.11
Classifier: Programming Language :: Python :: 3
Classifier: Programming Language :: Python :: 3.11
Classifier: Programming Language :: Python :: 3.12
Classifier: Programming Language :: Python :: 3.13
Requires-Dist: numpy (>=2.2.2,<3.0.0)
